doan_soc_nios_fixed_full/sobel_edge.v
module sobel_edge (
    clk,
    rst_n,
    gray_valid_in,
    gray8_in,
    edge_valid_out,
    edge_pixel_out
);

    parameter IMG_WIDTH  = 320;
    parameter IMG_HEIGHT = 240;
    parameter THRESHOLD  = 175;

    input clk;
    input rst_n;

    input gray_valid_in;
    input [7:0] gray8_in;

    output edge_valid_out;
    output [15:0] edge_pixel_out;

    reg edge_valid_out;
    reg [15:0] edge_pixel_out;

    // =========================================================
    // Line buffers
    // =========================================================

    reg [7:0] line_buffer_1 [0:IMG_WIDTH-1];
    reg [7:0] line_buffer_2 [0:IMG_WIDTH-1];

    reg [15:0] x;
    reg [15:0] y;

    integer i;

    // =========================================================
    // Stage 1: lấy top/mid/bot pixel
    // =========================================================

    reg valid_s1;
    reg [15:0] x_s1;
    reg [15:0] y_s1;

    reg [7:0] top_s1;
    reg [7:0] mid_s1;
    reg [7:0] bot_s1;

    // =========================================================
    // Window shift registers
    // =========================================================

    reg [7:0] p00;
    reg [7:0] p01;
    reg [7:0] p02;

    reg [7:0] p10;
    reg [7:0] p11;
    reg [7:0] p12;

    reg [7:0] p20;
    reg [7:0] p21;
    reg [7:0] p22;

    // =========================================================
    // Stage 2: register window 3x3
    // =========================================================

    reg valid_s2;
    reg [15:0] x_s2;
    reg [15:0] y_s2;

    reg [7:0] w00_s2;
    reg [7:0] w01_s2;
    reg [7:0] w02_s2;

    reg [7:0] w10_s2;
    reg [7:0] w11_s2;
    reg [7:0] w12_s2;

    reg [7:0] w20_s2;
    reg [7:0] w21_s2;
    reg [7:0] w22_s2;

    // =========================================================
    // Stage 3: Gx, Gy
    // =========================================================

    reg valid_s3;
    reg [15:0] x_s3;
    reg [15:0] y_s3;

    reg signed [15:0] gx_s3;
    reg signed [15:0] gy_s3;

    // =========================================================
    // Stage 4: abs
    // =========================================================

    reg valid_s4;
    reg [15:0] x_s4;
    reg [15:0] y_s4;

    reg [15:0] abs_gx_s4;
    reg [15:0] abs_gy_s4;

    // =========================================================
    // Stage 5: edge magnitude
    // =========================================================

    reg valid_s5;
    reg [15:0] x_s5;
    reg [15:0] y_s5;

    reg [16:0] edge_mag_s5;

    // =========================================================
    // Main pipeline
    // =========================================================

    always @(posedge clk or negedge rst_n) begin
        if (rst_n == 1'b0) begin
            x <= 16'd0;
            y <= 16'd0;

            valid_s1 <= 1'b0;
            valid_s2 <= 1'b0;
            valid_s3 <= 1'b0;
            valid_s4 <= 1'b0;
            valid_s5 <= 1'b0;

            edge_valid_out <= 1'b0;
            edge_pixel_out <= 16'h0000;

            x_s1 <= 16'd0;
            y_s1 <= 16'd0;
            x_s2 <= 16'd0;
            y_s2 <= 16'd0;
            x_s3 <= 16'd0;
            y_s3 <= 16'd0;
            x_s4 <= 16'd0;
            y_s4 <= 16'd0;
            x_s5 <= 16'd0;
            y_s5 <= 16'd0;

            top_s1 <= 8'd0;
            mid_s1 <= 8'd0;
            bot_s1 <= 8'd0;

            p00 <= 8'd0;
            p01 <= 8'd0;
            p02 <= 8'd0;

            p10 <= 8'd0;
            p11 <= 8'd0;
            p12 <= 8'd0;

            p20 <= 8'd0;
            p21 <= 8'd0;
            p22 <= 8'd0;

            w00_s2 <= 8'd0;
            w01_s2 <= 8'd0;
            w02_s2 <= 8'd0;

            w10_s2 <= 8'd0;
            w11_s2 <= 8'd0;
            w12_s2 <= 8'd0;

            w20_s2 <= 8'd0;
            w21_s2 <= 8'd0;
            w22_s2 <= 8'd0;

            gx_s3 <= 16'sd0;
            gy_s3 <= 16'sd0;

            abs_gx_s4 <= 16'd0;
            abs_gy_s4 <= 16'd0;
            edge_mag_s5 <= 17'd0;

            for (i = 0; i < IMG_WIDTH; i = i + 1) begin
                line_buffer_1[i] <= 8'd0;
                line_buffer_2[i] <= 8'd0;
            end

        end else begin

            // valid pipeline
            valid_s1 <= gray_valid_in;
            valid_s2 <= valid_s1;
            valid_s3 <= valid_s2;
            valid_s4 <= valid_s3;
            valid_s5 <= valid_s4;

            edge_valid_out <= valid_s5;

            // =================================================
            // Stage 1: lấy 3 pixel theo cột hiện tại
            // =================================================

            if (gray_valid_in) begin
                top_s1 <= line_buffer_2[x];
                mid_s1 <= line_buffer_1[x];
                bot_s1 <= gray8_in;

                x_s1 <= x;
                y_s1 <= y;

                line_buffer_2[x] <= line_buffer_1[x];
                line_buffer_1[x] <= gray8_in;

                if (x == IMG_WIDTH - 1) begin
                    x <= 16'd0;

                    if (y == IMG_HEIGHT - 1)
                        y <= 16'd0;
                    else
                        y <= y + 16'd1;
                end else begin
                    x <= x + 16'd1;
                end
            end

            // =================================================
            // Stage 2: tạo cửa sổ 3x3
            // =================================================

            if (valid_s1) begin
                x_s2 <= x_s1;
                y_s2 <= y_s1;

                w00_s2 <= p01;
                w01_s2 <= p02;
                w02_s2 <= top_s1;

                w10_s2 <= p11;
                w11_s2 <= p12;
                w12_s2 <= mid_s1;

                w20_s2 <= p21;
                w21_s2 <= p22;
                w22_s2 <= bot_s1;

                if (x_s1 == 16'd0) begin
                    p00 <= 8'd0;
                    p01 <= 8'd0;
                    p02 <= top_s1;

                    p10 <= 8'd0;
                    p11 <= 8'd0;
                    p12 <= mid_s1;

                    p20 <= 8'd0;
                    p21 <= 8'd0;
                    p22 <= bot_s1;
                end else begin
                    p00 <= p01;
                    p01 <= p02;
                    p02 <= top_s1;

                    p10 <= p11;
                    p11 <= p12;
                    p12 <= mid_s1;

                    p20 <= p21;
                    p21 <= p22;
                    p22 <= bot_s1;
                end
            end

            // =================================================
            // Stage 3: tính Gx, Gy
            // =================================================

            if (valid_s2) begin
                x_s3 <= x_s2;
                y_s3 <= y_s2;

                gx_s3 <=
                    $signed({1'b0, w02_s2}) - $signed({1'b0, w00_s2}) +
                    (($signed({1'b0, w12_s2}) - $signed({1'b0, w10_s2})) <<< 1) +
                    $signed({1'b0, w22_s2}) - $signed({1'b0, w20_s2});

                gy_s3 <=
                    $signed({1'b0, w00_s2}) +
                    ($signed({1'b0, w01_s2}) <<< 1) +
                    $signed({1'b0, w02_s2}) -
                    $signed({1'b0, w20_s2}) -
                    ($signed({1'b0, w21_s2}) <<< 1) -
                    $signed({1'b0, w22_s2});
            end

            // =================================================
            // Stage 4: trị tuyệt đối
            // =================================================

            if (valid_s3) begin
                x_s4 <= x_s3;
                y_s4 <= y_s3;

                if (gx_s3 < 0)
                    abs_gx_s4 <= 16'sd0 - gx_s3;
                else
                    abs_gx_s4 <= gx_s3;

                if (gy_s3 < 0)
                    abs_gy_s4 <= 16'sd0 - gy_s3;
                else
                    abs_gy_s4 <= gy_s3;
            end

            // =================================================
            // Stage 5: edge magnitude
            // =================================================

            if (valid_s4) begin
                x_s5 <= x_s4;
                y_s5 <= y_s4;

                edge_mag_s5 <= abs_gx_s4 + abs_gy_s4;
            end

            // =================================================
            // Output
            // =================================================

            if (valid_s5) begin
                if ((x_s5 < 16'd2) ||
                    (y_s5 < 16'd2) ||
                    (x_s5 >= IMG_WIDTH) ||
                    (y_s5 >= IMG_HEIGHT)) begin

                    edge_pixel_out <= 16'h0000;

                end else begin

                    if (edge_mag_s5 > THRESHOLD)
                        edge_pixel_out <= 16'hFFFF;
                    else
                        edge_pixel_out <= 16'h0000;

                end
            end else begin
                edge_pixel_out <= 16'h0000;
            end
        end
    end

endmodule

doan_soc_nios_fixed_full/rgb565_to_gray.v
module rgb565_to_gray (
    clk,
    rst_n,
    valid_in,
    rgb565_in,
    valid_out,
    gray8_out,
    gray565_out
);

    input clk;
    input rst_n;
    input valid_in;
    input [15:0] rgb565_in;

    output valid_out;
    output [7:0] gray8_out;
    output [15:0] gray565_out;

    reg valid_out;
    reg [7:0] gray8_out;
    reg [15:0] gray565_out;

    wire [4:0] r5;
    wire [5:0] g6;
    wire [4:0] b5;

    wire [7:0] r8;
    wire [7:0] g8;
    wire [7:0] b8;

    wire [7:0] gray_fast;

    assign r5 = rgb565_in[15:11];
    assign g6 = rgb565_in[10:5];
    assign b5 = rgb565_in[4:0];

    assign r8 = {r5, r5[4:2]};
    assign g8 = {g6, g6[5:4]};
    assign b8 = {b5, b5[4:2]};

    assign gray_fast = (r8 >> 2) + (g8 >> 1) + (b8 >> 2);

    always @(posedge clk or negedge rst_n) begin
        if (rst_n == 1'b0) begin
            valid_out <= 1'b0;
            gray8_out <= 8'd0;
            gray565_out <= 16'h0000;
        end else begin
            valid_out <= valid_in;

            if (valid_in) begin
                gray8_out <= gray_fast;
                gray565_out <= {gray_fast[7:3], gray_fast[7:2], gray_fast[7:3]};
            end
        end
    end

endmodule

doan_soc_nios_fixed_full/tb_gray_sram_sobel_matrix.v
`timescale 1ns/1ps

module tb_gray_sram_sobel_matrix;

    localparam IMG_WIDTH  = 8;
    localparam IMG_HEIGHT = 6;
    localparam FRAME_SIZE = IMG_WIDTH * IMG_HEIGHT;
    localparam THRESHOLD  = 100;

    reg clk;
    reg rst_n;

    reg        rgb_valid_in;
    reg [15:0] rgb565_in;
    wire       gray_valid_out;
    wire [7:0] gray8_out;
    wire [15:0] gray565_out;

    reg        sobel_valid_in;
    reg [7:0]  sobel_gray_in;
    wire       sobel_valid_out;
    wire [15:0] sobel_pixel_out;

    reg [15:0] rgb_sram [0:FRAME_SIZE-1];
    reg [7:0]  gray_sram [0:FRAME_SIZE-1];
    reg [15:0] sobel_seq_sram [0:FRAME_SIZE-1];
    reg [15:0] sobel_addr_sram [0:FRAME_SIZE-1];

    integer x;
    integer y;
    integer k;
    integer gray_wr_addr;
    integer sobel_seq_wr_addr;
    integer corrected_addr;
    integer center_x;
    integer center_y;
    integer sample_x_s5;
    integer sample_y_s5;
    integer sample_edge_mag_s5;

    rgb565_to_gray u_gray (
        .clk(clk),
        .rst_n(rst_n),
        .valid_in(rgb_valid_in),
        .rgb565_in(rgb565_in),
        .valid_out(gray_valid_out),
        .gray8_out(gray8_out),
        .gray565_out(gray565_out)
    );

    sobel_edge #(
        .IMG_WIDTH(IMG_WIDTH),
        .IMG_HEIGHT(IMG_HEIGHT),
        .THRESHOLD(THRESHOLD)
    ) u_sobel (
        .clk(clk),
        .rst_n(rst_n),
        .gray_valid_in(sobel_valid_in),
        .gray8_in(sobel_gray_in),
        .edge_valid_out(sobel_valid_out),
        .edge_pixel_out(sobel_pixel_out)
    );

    function [15:0] gray_to_rgb565;
        input [7:0] gray;
        begin
            gray_to_rgb565 = {gray[7:3], gray[7:2], gray[7:3]};
        end
    endfunction

    task print_rgb565_matrix;
        begin
            $display("");
            $display("RGB SRAM matrix, RGB565 hex:");
            for (y = 0; y < IMG_HEIGHT; y = y + 1) begin
                $write("row %0d: ", y);
                for (x = 0; x < IMG_WIDTH; x = x + 1) begin
                    $write("%h ", rgb_sram[y * IMG_WIDTH + x]);
                end
                $write("\n");
            end
        end
    endtask

    task print_gray_matrix;
        begin
            $display("");
            $display("GRAY SRAM matrix, 8-bit decimal:");
            for (y = 0; y < IMG_HEIGHT; y = y + 1) begin
                $write("row %0d: ", y);
                for (x = 0; x < IMG_WIDTH; x = x + 1) begin
                    $write("%3d ", gray_sram[y * IMG_WIDTH + x]);
                end
                $write("\n");
            end
        end
    endtask

    task print_sobel_seq_matrix;
        begin
            $display("");
            $display("SOBEL SRAM if written sequentially, like edge_detect_write_offset:");
            for (y = 0; y < IMG_HEIGHT; y = y + 1) begin
                $write("row %0d: ", y);
                for (x = 0; x < IMG_WIDTH; x = x + 1) begin
                    if (sobel_seq_sram[y * IMG_WIDTH + x] == 16'hFFFF)
                        $write("255 ");
                    else
                        $write("  0 ");
                end
                $write("\n");
            end
        end
    endtask

    task print_sobel_addr_matrix;
        begin
            $display("");
            $display("SOBEL SRAM if written by corrected center address:");
            $display("correct_addr = (y_s5 - 1) * IMG_WIDTH + (x_s5 - 1)");
            for (y = 0; y < IMG_HEIGHT; y = y + 1) begin
                $write("row %0d: ", y);
                for (x = 0; x < IMG_WIDTH; x = x + 1) begin
                    if (sobel_addr_sram[y * IMG_WIDTH + x] == 16'hFFFF)
                        $write("255 ");
                    else
                        $write("  0 ");
                end
                $write("\n");
            end
        end
    endtask

    initial begin
        clk = 1'b0;
        forever #5 clk = ~clk;
    end

    initial begin
        for (k = 0; k < FRAME_SIZE; k = k + 1) begin
            rgb_sram[k] = 16'h0000;
            gray_sram[k] = 8'd0;
            sobel_seq_sram[k] = 16'h0000;
            sobel_addr_sram[k] = 16'h0000;
        end

        for (y = 0; y < IMG_HEIGHT; y = y + 1) begin
            for (x = 0; x < IMG_WIDTH; x = x + 1) begin
                // Left half dark, right half bright. This makes a vertical edge.
                if (x < 4)
                    rgb_sram[y * IMG_WIDTH + x] = gray_to_rgb565(20 + y);
                else
                    rgb_sram[y * IMG_WIDTH + x] = gray_to_rgb565(220 - y);
            end
        end
    end

    initial begin
        $dumpfile("tb_gray_sram_sobel_matrix.vcd");
        $dumpvars(0, tb_gray_sram_sobel_matrix);

        rst_n = 1'b0;
        rgb_valid_in = 1'b0;
        rgb565_in = 16'h0000;
        sobel_valid_in = 1'b0;
        sobel_gray_in = 8'd0;
        gray_wr_addr = 0;
        sobel_seq_wr_addr = 0;

        repeat (4) @(posedge clk);
        rst_n = 1'b1;
        repeat (2) @(posedge clk);

        print_rgb565_matrix;

        $display("");
        $display("==== RGB SRAM -> rgb565_to_gray -> write GRAY SRAM ====");
        for (k = 0; k < FRAME_SIZE; k = k + 1) begin
            @(negedge clk);
            rgb_valid_in = 1'b1;
            rgb565_in = rgb_sram[k];
        end

        @(negedge clk);
        rgb_valid_in = 1'b0;
        rgb565_in = 16'h0000;
        repeat (3) @(posedge clk);

        print_gray_matrix;

        $display("");
        $display("==== Read GRAY SRAM sequentially -> sobel_edge ====");
        for (k = 0; k < FRAME_SIZE; k = k + 1) begin
            @(negedge clk);
            sobel_valid_in = 1'b1;
            sobel_gray_in = gray_sram[k];
            $display("READ_GRAY  addr=%2d  x=%0d y=%0d  gray=%3d",
                     k, k % IMG_WIDTH, k / IMG_WIDTH, gray_sram[k]);
        end

        @(negedge clk);
        sobel_valid_in = 1'b0;
        sobel_gray_in = 8'd0;
        repeat (12) @(posedge clk);

        print_sobel_seq_matrix;
        print_sobel_addr_matrix;

        $display("");
        $display("Done. Open tb_gray_sram_sobel_matrix.vcd to inspect waveform.");
        $finish;
    end

    always @(posedge clk) begin
        if (gray_valid_out) begin
            gray_sram[gray_wr_addr] = gray8_out;
            $display("WRITE_GRAY addr=%2d  x=%0d y=%0d  gray8=%3d  gray565=%h",
                     gray_wr_addr,
                     gray_wr_addr % IMG_WIDTH,
                     gray_wr_addr / IMG_WIDTH,
                     gray8_out,
                     gray565_out);
            gray_wr_addr = gray_wr_addr + 1;
        end
    end

    always @(posedge clk) begin
        sample_x_s5 = u_sobel.x_s5;
        sample_y_s5 = u_sobel.y_s5;
        sample_edge_mag_s5 = u_sobel.edge_mag_s5;

        #1;

        if (sobel_valid_out) begin
            if (sobel_seq_wr_addr < FRAME_SIZE)
                sobel_seq_sram[sobel_seq_wr_addr] = sobel_pixel_out;

            center_x = sample_x_s5 - 1;
            center_y = sample_y_s5 - 1;
            corrected_addr = center_y * IMG_WIDTH + center_x;

            if ((sample_x_s5 >= 2) &&
                (sample_y_s5 >= 2) &&
                (sample_x_s5 < IMG_WIDTH) &&
                (sample_y_s5 < IMG_HEIGHT)) begin
                sobel_addr_sram[corrected_addr] = sobel_pixel_out;

                $display("SOBEL_OUT input_corner=(%0d,%0d) center=(%0d,%0d) mag=%4d pixel=%h | seq_addr=%2d corrected_addr=%2d",
                         sample_x_s5,
                         sample_y_s5,
                         center_x,
                         center_y,
                         sample_edge_mag_s5,
                         sobel_pixel_out,
                         sobel_seq_wr_addr,
                         corrected_addr);
            end else begin
                $display("SOBEL_OUT input_corner=(%0d,%0d) border/invalid mag=%4d pixel=%h | seq_addr=%2d corrected_addr=none",
                         sample_x_s5,
                         sample_y_s5,
                         sample_edge_mag_s5,
                         sobel_pixel_out,
                         sobel_seq_wr_addr);
            end

            sobel_seq_wr_addr = sobel_seq_wr_addr + 1;
        end
    end

endmodule

doan_soc_nios_fixed_full/tb_gray_sram_sobel_matrix.vcd
$date
	Sat May 30 16:28:27 2026
$end
$version
	ModelSim Version 10.1d
$end
$timescale
	1ps
$end
$scope module tb_gray_sram_sobel_matrix $end
$var parameter 32 ! IMG_WIDTH $end
$var parameter 32 " IMG_HEIGHT $end
$var parameter 32 # FRAME_SIZE $end
$var parameter 32 $ THRESHOLD $end
$var reg 1 % clk $end
$var reg 1 & rst_n $end
$var reg 1 ' rgb_valid_in $end
$var reg 16 ( rgb565_in [15:0] $end
$var wire 1 ) gray_valid_out $end
$var wire 1 * gray8_out [7] $end
$var wire 1 + gray8_out [6] $end
$var wire 1 , gray8_out [5] $end
$var wire 1 - gray8_out [4] $end
$var wire 1 . gray8_out [3] $end
$var wire 1 / gray8_out [2] $end
$var wire 1 0 gray8_out [1] $end
$var wire 1 1 gray8_out [0] $end
$var wire 1 2 gray565_out [15] $end
$var wire 1 3 gray565_out [14] $end
$var wire 1 4 gray565_out [13] $end
$var wire 1 5 gray565_out [12] $end
$var wire 1 6 gray565_out [11] $end
$var wire 1 7 gray565_out [10] $end
$var wire 1 8 gray565_out [9] $end
$var wire 1 9 gray565_out [8] $end
$var wire 1 : gray565_out [7] $end
$var wire 1 ; gray565_out [6] $end
$var wire 1 < gray565_out [5] $end
$var wire 1 = gray565_out [4] $end
$var wire 1 > gray565_out [3] $end
$var wire 1 ? gray565_out [2] $end
$var wire 1 @ gray565_out [1] $end
$var wire 1 A gray565_out [0] $end
$var reg 1 B sobel_valid_in $end
$var reg 8 C sobel_gray_in [7:0] $end
$var wire 1 D sobel_valid_out $end
$var wire 1 E sobel_pixel_out [15] $end
$var wire 1 F sobel_pixel_out [14] $end
$var wire 1 G sobel_pixel_out [13] $end
$var wire 1 H sobel_pixel_out [12] $end
$var wire 1 I sobel_pixel_out [11] $end
$var wire 1 J sobel_pixel_out [10] $end
$var wire 1 K sobel_pixel_out [9] $end
$var wire 1 L sobel_pixel_out [8] $end
$var wire 1 M sobel_pixel_out [7] $end
$var wire 1 N sobel_pixel_out [6] $end
$var wire 1 O sobel_pixel_out [5] $end
$var wire 1 P sobel_pixel_out [4] $end
$var wire 1 Q sobel_pixel_out [3] $end
$var wire 1 R sobel_pixel_out [2] $end
$var wire 1 S sobel_pixel_out [1] $end
$var wire 1 T sobel_pixel_out [0] $end
$var integer 32 U x $end
$var integer 32 V y $end
$var integer 32 W k $end
$var integer 32 X gray_wr_addr $end
$var integer 32 Y sobel_seq_wr_addr $end
$var integer 32 Z corrected_addr $end
$var integer 32 [ center_x $end
$var integer 32 \ center_y $end
$var integer 32 ] sample_x_s5 $end
$var integer 32 ^ sample_y_s5 $end
$var integer 32 _ sample_edge_mag_s5 $end
$scope function gray_to_rgb565 $end
$var reg 16 ` gray_to_rgb565 [15:0] $end
$var reg 8 a gray [7:0] $end
$upscope $end
$scope task print_rgb565_matrix $end
$upscope $end
$scope task print_gray_matrix $end
$upscope $end
$scope task print_sobel_seq_matrix $end
$upscope $end
$scope task print_sobel_addr_matrix $end
$upscope $end
$scope module u_gray $end
$var wire 1 b clk $end
$var wire 1 c rst_n $end
$var wire 1 d valid_in $end
$var wire 1 e rgb565_in [15] $end
$var wire 1 f rgb565_in [14] $end
$var wire 1 g rgb565_in [13] $end
$var wire 1 h rgb565_in [12] $end
$var wire 1 i rgb565_in [11] $end
$var wire 1 j rgb565_in [10] $end
$var wire 1 k rgb565_in [9] $end
$var wire 1 l rgb565_in [8] $end
$var wire 1 m rgb565_in [7] $end
$var wire 1 n rgb565_in [6] $end
$var wire 1 o rgb565_in [5] $end
$var wire 1 p rgb565_in [4] $end
$var wire 1 q rgb565_in [3] $end
$var wire 1 r rgb565_in [2] $end
$var wire 1 s rgb565_in [1] $end
$var wire 1 t rgb565_in [0] $end
$var reg 1 u valid_out $end
$var reg 8 v gray8_out [7:0] $end
$var reg 16 w gray565_out [15:0] $end
$var wire 1 x r5 [4] $end
$var wire 1 y r5 [3] $end
$var wire 1 z r5 [2] $end
$var wire 1 { r5 [1] $end
$var wire 1 | r5 [0] $end
$var wire 1 } g6 [5] $end
$var wire 1 ~ g6 [4] $end
$var wire 1 !! g6 [3] $end
$var wire 1 "! g6 [2] $end
$var wire 1 #! g6 [1] $end
$var wire 1 $! g6 [0] $end
$var wire 1 %! b5 [4] $end
$var wire 1 &! b5 [3] $end
$var wire 1 '! b5 [2] $end
$var wire 1 (! b5 [1] $end
$var wire 1 )! b5 [0] $end
$var wire 1 *! r8 [7] $end
$var wire 1 +! r8 [6] $end
$var wire 1 ,! r8 [5] $end
$var wire 1 -! r8 [4] $end
$var wire 1 .! r8 [3] $end
$var wire 1 /! r8 [2] $end
$var wire 1 0! r8 [1] $end
$var wire 1 1! r8 [0] $end
$var wire 1 2! g8 [7] $end
$var wire 1 3! g8 [6] $end
$var wire 1 4! g8 [5] $end
$var wire 1 5! g8 [4] $end
$var wire 1 6! g8 [3] $end
$var wire 1 7! g8 [2] $end
$var wire 1 8! g8 [1] $end
$var wire 1 9! g8 [0] $end
$var wire 1 :! b8 [7] $end
$var wire 1 ;! b8 [6] $end
$var wire 1 <! b8 [5] $end
$var wire 1 =! b8 [4] $end
$var wire 1 >! b8 [3] $end
$var wire 1 ?! b8 [2] $end
$var wire 1 @! b8 [1] $end
$var wire 1 A! b8 [0] $end
$var wire 1 B! gray_fast [7] $end
$var wire 1 C! gray_fast [6] $end
$var wire 1 D! gray_fast [5] $end
$var wire 1 E! gray_fast [4] $end
$var wire 1 F! gray_fast [3] $end
$var wire 1 G! gray_fast [2] $end
$var wire 1 H! gray_fast [1] $end
$var wire 1 I! gray_fast [0] $end
$upscope $end
$scope module u_sobel $end
$var parameter 32 J! IMG_WIDTH $end
$var parameter 32 K! IMG_HEIGHT $end
$var parameter 32 L! THRESHOLD $end
$var wire 1 M! clk $end
$var wire 1 N! rst_n $end
$var wire 1 O! gray_valid_in $end
$var wire 1 P! gray8_in [7] $end
$var wire 1 Q! gray8_in [6] $end
$var wire 1 R! gray8_in [5] $end
$var wire 1 S! gray8_in [4] $end
$var wire 1 T! gray8_in [3] $end
$var wire 1 U! gray8_in [2] $end
$var wire 1 V! gray8_in [1] $end
$var wire 1 W! gray8_in [0] $end
$var reg 1 X! edge_valid_out $end
$var reg 16 Y! edge_pixel_out [15:0] $end
$var reg 16 Z! x [15:0] $end
$var reg 16 [! y [15:0] $end
$var integer 32 \! i $end
$var reg 1 ]! valid_s1 $end
$var reg 16 ^! x_s1 [15:0] $end
$var reg 16 _! y_s1 [15:0] $end
$var reg 8 `! top_s1 [7:0] $end
$var reg 8 a! mid_s1 [7:0] $end
$var reg 8 b! bot_s1 [7:0] $end
$var reg 8 c! p00 [7:0] $end
$var reg 8 d! p01 [7:0] $end
$var reg 8 e! p02 [7:0] $end
$var reg 8 f! p10 [7:0] $end
$var reg 8 g! p11 [7:0] $end
$var reg 8 h! p12 [7:0] $end
$var reg 8 i! p20 [7:0] $end
$var reg 8 j! p21 [7:0] $end
$var reg 8 k! p22 [7:0] $end
$var reg 1 l! valid_s2 $end
$var reg 16 m! x_s2 [15:0] $end
$var reg 16 n! y_s2 [15:0] $end
$var reg 8 o! w00_s2 [7:0] $end
$var reg 8 p! w01_s2 [7:0] $end
$var reg 8 q! w02_s2 [7:0] $end
$var reg 8 r! w10_s2 [7:0] $end
$var reg 8 s! w11_s2 [7:0] $end
$var reg 8 t! w12_s2 [7:0] $end
$var reg 8 u! w20_s2 [7:0] $end
$var reg 8 v! w21_s2 [7:0] $end
$var reg 8 w! w22_s2 [7:0] $end
$var reg 1 x! valid_s3 $end
$var reg 16 y! x_s3 [15:0] $end
$var reg 16 z! y_s3 [15:0] $end
$var reg 16 {! gx_s3 [15:0] $end
$var reg 16 |! gy_s3 [15:0] $end
$var reg 1 }! valid_s4 $end
$var reg 16 ~! x_s4 [15:0] $end
$var reg 16 !" y_s4 [15:0] $end
$var reg 16 "" abs_gx_s4 [15:0] $end
$var reg 16 #" abs_gy_s4 [15:0] $end
$var reg 1 $" valid_s5 $end
$var reg 16 %" x_s5 [15:0] $end
$var reg 16 &" y_s5 [15:0] $end
$var reg 17 '" edge_mag_s5 [16:0] $end
$upscope $end
$upscope $end
$enddefinitions $end
#0
$dumpvars
0%
0&
0'
b0 (
0B
b0 C
0u
b0 v
b0 w
0X!
b0 Y!
b0 Z!
b0 [!
0]!
b0 ^!
b0 _!
b0 `!
b0 a!
b0 b!
b0 c!
b0 d!
b0 e!
b0 f!
b0 g!
b0 h!
b0 i!
b0 j!
b0 k!
0l!
b0 m!
b0 n!
b0 o!
b0 p!
b0 q!
b0 r!
b0 s!
b0 t!
b0 u!
b0 v!
b0 w!
0x!
b0 y!
b0 z!
b0 {!
b0 |!
0}!
b0 ~!
b0 !"
b0 ""
b0 #"
0$"
b0 %"
b0 &"
b0 '"
b1101011010111010 `
b11010111 a
b1000 !
b110 "
b110000 #
b1100100 $
b1000 J!
b110 K!
b1100100 L!
b1000 U
b110 V
b110000 W
b0 X
b0 Y
bx Z
bx [
bx \
bx ]
bx ^
bx _
b1000 \!
0)
01
00
0/
0.
0-
0,
0+
0*
0A
0@
0?
0>
0=
0<
0;
0:
09
08
07
06
05
04
03
02
0D
0T
0S
0R
0Q
0P
0O
0N
0M
0L
0K
0J
0I
0H
0G
0F
0E
0|
0{
0z
0y
0x
0$!
0#!
0"!
0!!
0~
0}
0)!
0(!
0'!
0&!
0%!
01!
00!
0/!
0.!
0-!
0,!
0+!
0*!
09!
08!
07!
06!
05!
04!
03!
02!
0A!
0@!
0?!
0>!
0=!
0<!
0;!
0:!
0I!
0H!
0G!
0F!
0E!
0D!
0C!
0B!
0W!
0V!
0U!
0T!
0S!
0R!
0Q!
0P!
0O!
0N!
0M!
0t
0s
0r
0q
0p
0o
0n
0m
0l
0k
0j
0i
0h
0g
0f
0e
0d
0c
0b
$end
#5000
1%
1b
1M!
b0 \!
b1 \!
b10 \!
b11 \!
b100 \!
b101 \!
b110 \!
b111 \!
b1000 \!
b0 ]
b0 ^
b0 _
#10000
0%
0b
0M!
#15000
1%
1b
1M!
b0 \!
b1 \!
b10 \!
b11 \!
b100 \!
b101 \!
b110 \!
b111 \!
b1000 \!
#20000
0%
0b
0M!
#25000
1%
1b
1M!
b0 \!
b1 \!
b10 \!
b11 \!
b100 \!
b101 \!
b110 \!
b111 \!
b1000 \!
#30000
0%
0b
0M!
#35000
1%
1b
1M!
b0 \!
b1 \!
b10 \!
b11 \!
b100 \!
b101 \!
b110 \!
b111 \!
b1000 \!
1&
1c
1N!
#40000
0%
0b
0M!
#45000
1%
1b
1M!
#50000
0%
0b
0M!
#55000
1%
1b
1M!
b0 V
b0 U
b1 U
b10 U
b11 U
b100 U
b101 U
b110 U
b111 U
b1000 U
b1 V
b0 U
b1 U
b10 U
b11 U
b100 U
b101 U
b110 U
b111 U
b1000 U
b10 V
b0 U
b1 U
b10 U
b11 U
b100 U
b101 U
b110 U
b111 U
b1000 U
b11 V
b0 U
b1 U
b10 U
b11 U
b100 U
b101 U
b110 U
b111 U
b1000 U
b100 V
b0 U
b1 U
b10 U
b11 U
b100 U
b101 U
b110 U
b111 U
b1000 U
b101 V
b0 U
b1 U
b10 U
b11 U
b100 U
b101 U
b110 U
b111 U
b1000 U
b110 V
b0 W
#60000
0%
0b
0M!
1'
b1000010100010 (
b1 W
1d
1s
1o
1m
1h
1{
1$!
1"!
1(!
1=!
17!
15!
1-!
1H!
1E!
#65000
1%
1b
1M!
1u
b10010 v
b1000010000010 w
1)
1@
1:
15
10
1-
#70000
0%
0b
0M!
b10 W
#75000
1%
1b
1M!
b1 X
#80000
0%
0b
0M!
b11 W
#85000
1%
1b
1M!
b10 X
#90000
0%
0b
0M!
b100 W
#95000
1%
1b
1M!
b11 X
#100000
0%
0b
0M!
b1101111011111011 (
b101 W
1t
1q
1p
1n
1k
1j
1i
1f
1e
1|
1y
1x
1#!
1~
1}
1)!
1&!
1%!
1@!
1?!
1>!
1;!
1:!
19!
18!
16!
13!
12!
10!
1/!
1.!
1+!
1*!
1I!
0H!
1G!
1F!
1C!
1B!
#105000
1%
1b
1M!
b100 X
b11011101 v
b1101111011111011 w
1A
1>
1=
1<
1;
18
17
16
13
12
11
00
1/
1.
1+
1*
#110000
0%
0b
0M!
b110 W
#115000
1%
1b
1M!
b101 X
#120000
0%
0b
0M!
b111 W
#125000
1%
1b
1M!
b110 X
#130000
0%
0b
0M!
b1000 W
#135000
1%
1b
1M!
b111 X
#140000
0%
0b
0M!
b1000010100010 (
b1001 W
0t
0q
0p
0n
0k
0j
0i
0f
0e
0|
0y
0x
0#!
0~
0}
0)!
0&!
0%!
0@!
0?!
0>!
0;!
0:!
09!
08!
06!
03!
02!
00!
0/!
0.!
0+!
0*!
0I!
1H!
0G!
0F!
0C!
0B!
#145000
1%
1b
1M!
b1000 X
b10010 v
b1000010000010 w
0A
0>
0=
0<
0;
08
07
06
03
02
01
10
0/
0.
0+
0*
#150000
0%
0b
0M!
b1010 W
#155000
1%
1b
1M!
b1001 X
#160000
0%
0b
0M!
b1011 W
#165000
1%
1b
1M!
b1010 X
#170000
0%
0b
0M!
b1100 W
#175000
1%
1b
1M!
b1011 X
#180000
0%
0b
0M!
b1101111011011011 (
b1101 W
1t
1q
1p
0o
1n
1k
1j
1i
1f
1e
1|
1y
1x
0$!
1#!
1~
1}
1)!
1&!
1%!
1@!
1?!
1>!
1;!
1:!
19!
18!
07!
16!
13!
12!
10!
1/!
1.!
1+!
1*!
1I!
1F!
1C!
1B!
