doan_soc_nios_fixed_full/sobel_edge.v
module sobel_edge (
    clk,
    rst_n,
    gray_valid_in,
    gray8_in,
    edge_valid_out,
    edge_pixel_out
);

    parameter IMG_WIDTH  = 320;
    parameter IMG_HEIGHT = 240;
    parameter THRESHOLD  = 175;

    input clk;
    input rst_n;

    input gray_valid_in;
    input [7:0] gray8_in;

    output edge_valid_out;
    output [15:0] edge_pixel_out;

    reg edge_valid_out;
    reg [15:0] edge_pixel_out;

    // =========================================================
    // Line buffers
    // =========================================================

    reg [7:0] line_buffer_1 [0:IMG_WIDTH-1];
    reg [7:0] line_buffer_2 [0:IMG_WIDTH-1];

    reg [15:0] x;
    reg [15:0] y;

    integer i;

    // =========================================================
    // Stage 1: lấy top/mid/bot pixel
    // =========================================================

    reg valid_s1;
    reg [15:0] x_s1;
    reg [15:0] y_s1;

    reg [7:0] top_s1;
    reg [7:0] mid_s1;
    reg [7:0] bot_s1;

    // =========================================================
    // Window shift registers
    // =========================================================

    reg [7:0] p00;
    reg [7:0] p01;
    reg [7:0] p02;

    reg [7:0] p10;
    reg [7:0] p11;
    reg [7:0] p12;

    reg [7:0] p20;
    reg [7:0] p21;
    reg [7:0] p22;

    // =========================================================
    // Stage 2: register window 3x3
    // =========================================================

    reg valid_s2;
    reg [15:0] x_s2;
    reg [15:0] y_s2;

    reg [7:0] w00_s2;
    reg [7:0] w01_s2;
    reg [7:0] w02_s2;

    reg [7:0] w10_s2;
    reg [7:0] w11_s2;
    reg [7:0] w12_s2;

    reg [7:0] w20_s2;
    reg [7:0] w21_s2;
    reg [7:0] w22_s2;

    // =========================================================
    // Stage 3: Gx, Gy
    // =========================================================

    reg valid_s3;
    reg [15:0] x_s3;
    reg [15:0] y_s3;

    reg signed [15:0] gx_s3;
    reg signed [15:0] gy_s3;

    // =========================================================
    // Stage 4: abs
    // =========================================================

    reg valid_s4;
    reg [15:0] x_s4;
    reg [15:0] y_s4;

    reg [15:0] abs_gx_s4;
    reg [15:0] abs_gy_s4;

    // =========================================================
    // Stage 5: edge magnitude
    // =========================================================

    reg valid_s5;
    reg [15:0] x_s5;
    reg [15:0] y_s5;

    reg [16:0] edge_mag_s5;

    // =========================================================
    // Main pipeline
    // =========================================================

    always @(posedge clk or negedge rst_n) begin
        if (rst_n == 1'b0) begin
            x <= 16'd0;
            y <= 16'd0;

            valid_s1 <= 1'b0;
            valid_s2 <= 1'b0;
            valid_s3 <= 1'b0;
            valid_s4 <= 1'b0;
            valid_s5 <= 1'b0;

            edge_valid_out <= 1'b0;
            edge_pixel_out <= 16'h0000;

            x_s1 <= 16'd0;
            y_s1 <= 16'd0;
            x_s2 <= 16'd0;
            y_s2 <= 16'd0;
            x_s3 <= 16'd0;
            y_s3 <= 16'd0;
            x_s4 <= 16'd0;
            y_s4 <= 16'd0;
            x_s5 <= 16'd0;
            y_s5 <= 16'd0;

            top_s1 <= 8'd0;
            mid_s1 <= 8'd0;
            bot_s1 <= 8'd0;

            p00 <= 8'd0;
            p01 <= 8'd0;
            p02 <= 8'd0;

            p10 <= 8'd0;
            p11 <= 8'd0;
            p12 <= 8'd0;

            p20 <= 8'd0;
            p21 <= 8'd0;
            p22 <= 8'd0;

            w00_s2 <= 8'd0;
            w01_s2 <= 8'd0;
            w02_s2 <= 8'd0;

            w10_s2 <= 8'd0;
            w11_s2 <= 8'd0;
            w12_s2 <= 8'd0;

            w20_s2 <= 8'd0;
            w21_s2 <= 8'd0;
            w22_s2 <= 8'd0;

            gx_s3 <= 16'sd0;
            gy_s3 <= 16'sd0;

            abs_gx_s4 <= 16'd0;
            abs_gy_s4 <= 16'd0;
            edge_mag_s5 <= 17'd0;

            for (i = 0; i < IMG_WIDTH; i = i + 1) begin
                line_buffer_1[i] <= 8'd0;
                line_buffer_2[i] <= 8'd0;
            end

        end else begin

            // valid pipeline
            valid_s1 <= gray_valid_in;
            valid_s2 <= valid_s1;
            valid_s3 <= valid_s2;
            valid_s4 <= valid_s3;
            valid_s5 <= valid_s4;

            edge_valid_out <= valid_s5;

            // =================================================
            // Stage 1: lấy 3 pixel theo cột hiện tại
            // =================================================

            if (gray_valid_in) begin
                top_s1 <= line_buffer_2[x];
                mid_s1 <= line_buffer_1[x];
                bot_s1 <= gray8_in;

                x_s1 <= x;
                y_s1 <= y;

                line_buffer_2[x] <= line_buffer_1[x];
                line_buffer_1[x] <= gray8_in;

                if (x == IMG_WIDTH - 1) begin
                    x <= 16'd0;

                    if (y == IMG_HEIGHT - 1)
                        y <= 16'd0;
                    else
                        y <= y + 16'd1;
                end else begin
                    x <= x + 16'd1;
                end
            end

            // =================================================
            // Stage 2: tạo cửa sổ 3x3
            // =================================================

            if (valid_s1) begin
                x_s2 <= x_s1;
                y_s2 <= y_s1;

                w00_s2 <= p01;
                w01_s2 <= p02;
                w02_s2 <= top_s1;

                w10_s2 <= p11;
                w11_s2 <= p12;
                w12_s2 <= mid_s1;

                w20_s2 <= p21;
                w21_s2 <= p22;
                w22_s2 <= bot_s1;

                if (x_s1 == 16'd0) begin
                    p00 <= 8'd0;
                    p01 <= 8'd0;
                    p02 <= top_s1;

                    p10 <= 8'd0;
                    p11 <= 8'd0;
                    p12 <= mid_s1;

                    p20 <= 8'd0;
                    p21 <= 8'd0;
                    p22 <= bot_s1;
                end else begin
                    p00 <= p01;
                    p01 <= p02;
                    p02 <= top_s1;

                    p10 <= p11;
                    p11 <= p12;
                    p12 <= mid_s1;

                    p20 <= p21;
                    p21 <= p22;
                    p22 <= bot_s1;
                end
            end

            // =================================================
            // Stage 3: tính Gx, Gy
            // =================================================

            if (valid_s2) begin
                x_s3 <= x_s2;
                y_s3 <= y_s2;

                gx_s3 <=
                    $signed({1'b0, w02_s2}) - $signed({1'b0, w00_s2}) +
                    (($signed({1'b0, w12_s2}) - $signed({1'b0, w10_s2})) <<< 1) +
                    $signed({1'b0, w22_s2}) - $signed({1'b0, w20_s2});

                gy_s3 <=
                    $signed({1'b0, w00_s2}) +
                    ($signed({1'b0, w01_s2}) <<< 1) +
                    $signed({1'b0, w02_s2}) -
                    $signed({1'b0, w20_s2}) -
                    ($signed({1'b0, w21_s2}) <<< 1) -
                    $signed({1'b0, w22_s2});
            end

            // =================================================
            // Stage 4: trị tuyệt đối
            // =================================================

            if (valid_s3) begin
                x_s4 <= x_s3;
                y_s4 <= y_s3;

                if (gx_s3 < 0)
                    abs_gx_s4 <= 16'sd0 - gx_s3;
                else
                    abs_gx_s4 <= gx_s3;

                if (gy_s3 < 0)
                    abs_gy_s4 <= 16'sd0 - gy_s3;
                else
                    abs_gy_s4 <= gy_s3;
            end

            // =================================================
            // Stage 5: edge magnitude
            // =================================================

            if (valid_s4) begin
                x_s5 <= x_s4;
                y_s5 <= y_s4;

                edge_mag_s5 <= abs_gx_s4 + abs_gy_s4;
            end

            // =================================================
            // Output
            // =================================================

            if (valid_s5) begin
                if ((x_s5 < 16'd2) ||
                    (y_s5 < 16'd2) ||
                    (x_s5 >= IMG_WIDTH) ||
                    (y_s5 >= IMG_HEIGHT)) begin

                    edge_pixel_out <= 16'h0000;

                end else begin

                    if (edge_mag_s5 > THRESHOLD)
                        edge_pixel_out <= 16'hFFFF;
                    else
                        edge_pixel_out <= 16'h0000;

                end
            end else begin
                edge_pixel_out <= 16'h0000;
            end
        end
    end

endmodule

doan_soc_nios_fixed_full/tb_sobel_edge.v
`timescale 1ns/1ps

module tb_sobel_edge;

    localparam IMG_WIDTH  = 8;
    localparam IMG_HEIGHT = 6;
    localparam THRESHOLD  = 100;
    localparam FRAME_SIZE = IMG_WIDTH * IMG_HEIGHT;

    reg clk;
    reg rst_n;
    reg gray_valid_in;
    reg [7:0] gray8_in;

    wire edge_valid_out;
    wire [15:0] edge_pixel_out;

    reg [7:0] frame [0:FRAME_SIZE-1];

    integer x;
    integer y;
    integer k;
    integer out_count;
    integer center_x;
    integer center_y;

    sobel_edge #(
        .IMG_WIDTH(IMG_WIDTH),
        .IMG_HEIGHT(IMG_HEIGHT),
        .THRESHOLD(THRESHOLD)
    ) dut (
        .clk(clk),
        .rst_n(rst_n),
        .gray_valid_in(gray_valid_in),
        .gray8_in(gray8_in),
        .edge_valid_out(edge_valid_out),
        .edge_pixel_out(edge_pixel_out)
    );

    initial begin
        clk = 1'b0;
        forever #5 clk = ~clk;
    end

    initial begin
        for (y = 0; y < IMG_HEIGHT; y = y + 1) begin
            for (x = 0; x < IMG_WIDTH; x = x + 1) begin
                // Left half dark, right half bright. This creates a vertical edge.
                if (x < (IMG_WIDTH / 2))
                    frame[y * IMG_WIDTH + x] = 8'd0;
                else
                    frame[y * IMG_WIDTH + x] = 8'd255;
            end
        end
    end

    initial begin
        $dumpfile("tb_sobel_edge.vcd");
        $dumpvars(0, tb_sobel_edge);

        rst_n = 1'b0;
        gray_valid_in = 1'b0;
        gray8_in = 8'd0;
        out_count = 0;

        repeat (4) @(posedge clk);
        rst_n = 1'b1;
        repeat (2) @(posedge clk);

        $display("Feed image in raster order: (0,0), (1,0), ... (7,0), (0,1), ...");
        $display("When input corner is x_s5/y_s5, Sobel output belongs to center x_s5-1/y_s5-1.");
        $display("");
        $display("time  in_x in_y  center_x center_y  pixel  edge_mag");

        for (k = 0; k < FRAME_SIZE; k = k + 1) begin
            @(negedge clk);
            gray_valid_in = 1'b1;
            gray8_in = frame[k];
        end

        @(negedge clk);
        gray_valid_in = 1'b0;
        gray8_in = 8'd0;

        // Let the 5-stage Sobel pipeline drain.
        repeat (12) @(posedge clk);

        $display("");
        $display("Total valid output cycles: %0d", out_count);
        $finish;
    end

    always @(posedge clk) begin
        if (edge_valid_out) begin
            out_count = out_count + 1;
            center_x = dut.x_s5 - 1;
            center_y = dut.y_s5 - 1;
            $display("%4t  %4d %4d  %8d %8d  %h  %7d",
                     $time,
                     dut.x_s5,
                     dut.y_s5,
                     center_x,
                     center_y,
                     edge_pixel_out,
                     dut.edge_mag_s5);
        end
    end

endmodule

doan_soc_nios_fixed_full/tb_sobel_edge.vcd
$date
	Sat May 30 16:27:56 2026
$end
$version
	ModelSim Version 10.1d
$end
$timescale
	1ps
$end
$scope module tb_sobel_edge $end
$var parameter 32 ! IMG_WIDTH $end
$var parameter 32 " IMG_HEIGHT $end
$var parameter 32 # THRESHOLD $end
$var parameter 32 $ FRAME_SIZE $end
$var reg 1 % clk $end
$var reg 1 & rst_n $end
$var reg 1 ' gray_valid_in $end
$var reg 8 ( gray8_in [7:0] $end
$var wire 1 ) edge_valid_out $end
$var wire 1 * edge_pixel_out [15] $end
$var wire 1 + edge_pixel_out [14] $end
$var wire 1 , edge_pixel_out [13] $end
$var wire 1 - edge_pixel_out [12] $end
$var wire 1 . edge_pixel_out [11] $end
$var wire 1 / edge_pixel_out [10] $end
$var wire 1 0 edge_pixel_out [9] $end
$var wire 1 1 edge_pixel_out [8] $end
$var wire 1 2 edge_pixel_out [7] $end
$var wire 1 3 edge_pixel_out [6] $end
$var wire 1 4 edge_pixel_out [5] $end
$var wire 1 5 edge_pixel_out [4] $end
$var wire 1 6 edge_pixel_out [3] $end
$var wire 1 7 edge_pixel_out [2] $end
$var wire 1 8 edge_pixel_out [1] $end
$var wire 1 9 edge_pixel_out [0] $end
$var integer 32 : x $end
$var integer 32 ; y $end
$var integer 32 < k $end
$var integer 32 = out_count $end
$var integer 32 > center_x $end
$var integer 32 ? center_y $end
$scope module dut $end
$var parameter 32 @ IMG_WIDTH $end
$var parameter 32 A IMG_HEIGHT $end
$var parameter 32 B THRESHOLD $end
$var wire 1 C clk $end
$var wire 1 D rst_n $end
$var wire 1 E gray_valid_in $end
$var wire 1 F gray8_in [7] $end
$var wire 1 G gray8_in [6] $end
$var wire 1 H gray8_in [5] $end
$var wire 1 I gray8_in [4] $end
$var wire 1 J gray8_in [3] $end
$var wire 1 K gray8_in [2] $end
$var wire 1 L gray8_in [1] $end
$var wire 1 M gray8_in [0] $end
$var reg 1 N edge_valid_out $end
$var reg 16 O edge_pixel_out [15:0] $end
$var reg 16 P x [15:0] $end
$var reg 16 Q y [15:0] $end
$var integer 32 R i $end
$var reg 1 S valid_s1 $end
$var reg 16 T x_s1 [15:0] $end
$var reg 16 U y_s1 [15:0] $end
$var reg 8 V top_s1 [7:0] $end
$var reg 8 W mid_s1 [7:0] $end
$var reg 8 X bot_s1 [7:0] $end
$var reg 8 Y p00 [7:0] $end
$var reg 8 Z p01 [7:0] $end
$var reg 8 [ p02 [7:0] $end
$var reg 8 \ p10 [7:0] $end
$var reg 8 ] p11 [7:0] $end
$var reg 8 ^ p12 [7:0] $end
$var reg 8 _ p20 [7:0] $end
$var reg 8 ` p21 [7:0] $end
$var reg 8 a p22 [7:0] $end
$var reg 1 b valid_s2 $end
$var reg 16 c x_s2 [15:0] $end
$var reg 16 d y_s2 [15:0] $end
$var reg 8 e w00_s2 [7:0] $end
$var reg 8 f w01_s2 [7:0] $end
$var reg 8 g w02_s2 [7:0] $end
$var reg 8 h w10_s2 [7:0] $end
$var reg 8 i w11_s2 [7:0] $end
$var reg 8 j w12_s2 [7:0] $end
$var reg 8 k w20_s2 [7:0] $end
$var reg 8 l w21_s2 [7:0] $end
$var reg 8 m w22_s2 [7:0] $end
$var reg 1 n valid_s3 $end
$var reg 16 o x_s3 [15:0] $end
$var reg 16 p y_s3 [15:0] $end
$var reg 16 q gx_s3 [15:0] $end
$var reg 16 r gy_s3 [15:0] $end
$var reg 1 s valid_s4 $end
$var reg 16 t x_s4 [15:0] $end
$var reg 16 u y_s4 [15:0] $end
$var reg 16 v abs_gx_s4 [15:0] $end
$var reg 16 w abs_gy_s4 [15:0] $end
$var reg 1 x valid_s5 $end
$var reg 16 y x_s5 [15:0] $end
$var reg 16 z y_s5 [15:0] $end
$var reg 17 { edge_mag_s5 [16:0] $end
$upscope $end
$upscope $end
$enddefinitions $end
#0
$dumpvars
0%
0&
0'
b0 (
0N
b0 O
b0 P
b0 Q
0S
b0 T
b0 U
b0 V
b0 W
b0 X
b0 Y
b0 Z
b0 [
b0 \
b0 ]
b0 ^
b0 _
b0 `
b0 a
0b
b0 c
b0 d
b0 e
b0 f
b0 g
b0 h
b0 i
b0 j
b0 k
b0 l
b0 m
0n
b0 o
b0 p
b0 q
b0 r
0s
b0 t
b0 u
b0 v
b0 w
0x
b0 y
b0 z
b0 {
b1000 !
b110 "
b1100100 #
b110000 $
b1000 @
b110 A
b1100100 B
b1000 :
b110 ;
bx <
b0 =
bx >
bx ?
b1000 R
0)
09
08
07
06
05
04
03
02
01
00
0/
0.
0-
0,
0+
0*
0M
0L
0K
0J
0I
0H
0G
0F
0E
0D
0C
$end
#5000
1%
1C
b0 R
b1 R
b10 R
b11 R
b100 R
b101 R
b110 R
b111 R
b1000 R
#10000
0%
0C
#15000
1%
1C
b0 R
b1 R
b10 R
b11 R
b100 R
b101 R
b110 R
b111 R
b1000 R
#20000
0%
0C
#25000
1%
1C
b0 R
b1 R
b10 R
b11 R
b100 R
b101 R
b110 R
b111 R
b1000 R
#30000
0%
0C
#35000
1%
1C
b0 R
b1 R
b10 R
b11 R
b100 R
b101 R
b110 R
b111 R
b1000 R
1&
1D
#40000
0%
0C
#45000
1%
1C
#50000
0%
0C
#55000
1%
1C
b0 <
#60000
0%
0C
1'
b1 <
1E
#65000
1%
1C
1S
b1 P
#70000
0%
0C
b10 <
#75000
1%
1C
1b
b1 T
b10 P
#80000
0%
0C
b11 <
#85000
1%
1C
1n
b10 T
b11 P
b1 c
#90000
0%
0C
b100 <
#95000
1%
1C
1s
b11 T
b100 P
b10 c
b1 o
#100000
0%
0C
b11111111 (
b101 <
1M
1L
1K
1J
1I
1H
1G
1F
#105000
1%
1C
1x
b11111111 X
b100 T
b101 P
b11 c
b10 o
b1 t
#110000
0%
0C
b110 <
#115000
1%
1C
1N
b101 T
b110 P
b100 c
b11111111 m
b11111111 a
b11 o
b10 t
b1 y
1)
#120000
0%
0C
b111 <
#125000
1%
1C
b1 =
b0 >
b11111111111111111111111111111111 ?
b110 T
b111 P
b101 c
b11111111 l
b11111111 `
b100 o
b11111111 q
b1111111100000001 r
b11 t
b10 y
#130000
0%
0C
b1000 <
#135000
1%
1C
b10 =
b1 >
b111 T
b0 P
b1 Q
b110 c
b11111111 k
b11111111 _
b101 o
b1111110100000011 r
b100 t
b11111111 v
b11111111 w
b11 y
#140000
0%
0C
b0 (
b1001 <
0M
0L
0K
0J
0I
0H
0G
0F
#145000
1%
1C
b11 =
b10 >
b0 X
b0 T
b1 U
b1 P
b111 c
b110 o
b0 q
b1111110000000100 r
b101 t
b1011111101 w
b100 y
b111111110 {
#150000
0%
0C
b1010 <
#155000
1%
1C
b100 =
b11 >
b1 T
b10 P
b0 c
b1 d
b0 m
b0 _
b0 `
b0 a
b111 o
b110 t
b0 v
b1111111100 w
b101 y
b1111111100 {
#160000
0%
0C
b1011 <
#165000
1%
1C
b101 =
b100 >
b10 T
b11 P
b1 c
b0 k
b0 l
b0 o
b1 p
b1111111100000001 q
b1111110100000011 r
b111 t
b110 y
#170000
0%
0C
b1100 <
#175000
1%
1C
b110 =
b101 >
b11 T
b100 P
b10 c
b1 o
b0 q
b0 r
b0 t
b1 u
b11111111 v
b1011111101 w
b111 y
#180000
0%
0C
b11111111 (
b1101 <
1M
1L
1K
1J
1I
1H
1G
1F
#185000
1%
1C
b111 =
b110 >
b11111111 W
b11111111 X
b100 T
b101 P
b11 c
b10 o
b1 t
b0 v
b0 w
b0 y
b1 z
#190000
0%
0C
b1110 <
#195000
1%
1C
b1000 =
b11111111111111111111111111111111 >
b0 ?
b101 T
b110 P
b100 c
b11111111 j
b11111111 m
b11111111 ^
b11111111 a
b11 o
b10 t
b1 y
b0 {
#200000
0%
0C
b1111 <
#205000
1%
1C
b1001 =
b0 >
b110 T
b111 P
b101 c
b11111111 i
b11111111 l
b11111111 ]
b11111111 `
b100 o
b1011111101 q
b1111111100000001 r
b11 t
b10 y
#210000
0%
0C
b10000 <
#215000
1%
1C
b1010 =
b1 >
b111 T
b0 P
b10 Q
b110 c
b11111111 h
b11111111 k
b11111111 \
b11111111 _
b101 o
b1111110100000011 r
b100 t
b1011111101 v
b11111111 w
b11 y
#220000
0%
0C
b0 (
b10001 <
0M
0L
0K
0J
0I
0H
0G
0F
#225000
1%
1C
b1011 =
b10 >
b0 W
b0 X
b0 T
b10 U
b1 P
b111 c
b110 o
b0 q
b1111110000000100 r
b101 t
b1011111101 w
b100 y
b1111111100 {
#230000
0%
0C
b10010 <
#235000
1%
1C
b1100 =
b11 >
b1 T
b10 P
b0 c
b10 d
b0 j
b0 m
b0 \
b0 ]
b0 ^
b0 _
b0 `
b0 a
b111 o
b110 t
b0 v
b1111111100 w
b101 y
b10111111010 {
#240000
0%
0C
b10011 <
#245000
1%
1C
b1101 =
b100 >
b10 T
b11 P
b1 c
b0 h
b0 i
b0 k
b0 l
b0 o
b10 p
b1111110100000011 q
b1111110100000011 r
b111 t
b110 y
b1111111100 {
#250000
0%
0C
b10100 <
#255000
1%
1C
b1110 =
b101 >
b11 T
b100 P
b10 c
b1 o
b0 q
b0 r
b0 t
b10 u
b1011111101 v
b1011111101 w
b111 y
#260000
0%
0C
b11111111 (
b10101 <
1M
1L
1K
1J
1I
1H
1G
1F
#265000
1%
1C
b1111 =
b110 >
b11111111 V
b11111111 W
b11111111 X
b100 T
b101 P
b11 c
b10 o
b1 t
b0 v
b0 w
b0 y
b10 z
b10111111010 {
#270000
0%
0C
b10110 <
#275000
1%
1C
b10000 =
b11111111111111111111111111111111 >
b1 ?
b101 T
b110 P
b100 c
b11111111 g
b11111111 j
b11111111 m
b11111111 [
b11111111 ^
b11111111 a
b11 o
b10 t
b1 y
b0 {
#280000
0%
0C
b10111 <
#285000
1%
1C
b10001 =
b0 >
b110 T
b111 P
b101 c
b11111111 f
b11111111 i
b11111111 l
b11111111 Z
b11111111 ]
b11111111 `
b100 o
b1111111100 q
b11 t
b10 y
#290000
0%
0C
b11000 <
#295000
1%
1C
b10010 =
b1 >
b111 T
b0 P
b11 Q
b110 c
b11111111 e
b11111111 h
b11111111 k
b11111111 Y
b11111111 \
b11111111 _
b101 o
b100 t
b1111111100 v
b11 y
#300000
0%
0C
b0 (
b11001 <
0M
0L
0K
0J
0I
0H
0G
0F
#305000
1%
1C
b10011 =
b10 >
b0 V
b0 W
b0 X
b0 T
b11 U
b1 P
b111 c
b110 o
b0 q
b101 t
b100 y
b1111111100 {
#310000
0%
0C
b11010 <
#315000
1%
1C
b10100 =
b11 >
b1 T
b10 P
b0 c
b11 d
b0 g
b0 j
b0 m
b0 Y
b0 Z
b0 [
b0 \
b0 ]
b0 ^
b0 _
b0 `
b0 a
b111 o
b110 t
b0 v
b101 y
b1111111111111111 O
19
18
17
16
15
14
13
12
11
10
1/
1.
1-
1,
1+
1*
#320000
0%
0C
b11011 <
#325000
1%
1C
b10101 =
b100 >
b10 T
b11 P
b1 c
b0 e
b0 f
b0 h
b0 i
b0 k
b0 l
b0 o
b11 p
b1111110000000100 q
b111 t
b110 y
b0 {
#330000
0%
0C
b11100 <
#335000
1%
1C
b10110 =
b101 >
b11 T
b100 P
b10 c
b1 o
b0 q
b0 t
b11 u
b1111111100 v
b111 y
b0 O
09
08
07
06
05
04
03
02
01
00
0/
0.
0-
0,
0+
0*
#340000
0%
0C
b11111111 (
b11101 <
1M
1L
1K
1J
1I
1H
1G
1F
#345000
1%
1C
b10111 =
b110 >
b11111111 V
b11111111 W
b11111111 X
b100 T
b101 P
b11 c
b10 o
b1 t
b0 v
b0 y
b11 z
b1111111100 {
#350000
0%
0C
b11110 <
#355000
1%
1C
b11000 =
b11111111111111111111111111111111 >
b10 ?
b101 T
b110 P
b100 c
b11111111 g
b11111111 j
b11111111 m
b11111111 [
b11111111 ^
b11111111 a
b11 o
b10 t
b1 y
b0 {
#360000
0%
0C
b11111 <
#365000
1%
1C
b11001 =
b0 >
b110 T
b111 P
b101 c
b11111111 f
b11111111 i
b11111111 l
b11111111 Z
b11111111 ]
b11111111 `
b100 o
b1111111100 q
b11 t
b10 y
#370000
0%
0C
b100000 <
#375000
1%
1C
b11010 =
b1 >
b111 T
b0 P
b100 Q
b110 c
b11111111 e
b11111111 h
b11111111 k
b11111111 Y
b11111111 \
b11111111 _
b101 o
b100 t
b1111111100 v
b11 y
#380000
0%
0C
b0 (
b100001 <
0M
0L
0K
0J
0I
0H
0G
0F
#385000
1%
1C
b11011 =
b10 >
b0 V
b0 W
b0 X
b0 T
b100 U
b1 P
b111 c
b110 o
b0 q
b101 t
b100 y
b1111111100 {
#390000
0%
0C
b100010 <
#395000
1%
1C
b11100 =
b11 >
b1 T
b10 P
b0 c
b100 d
b0 g
b0 j
b0 m
b0 Y
b0 Z
b0 [
b0 \
b0 ]
b0 ^
b0 _
b0 `
b0 a
b111 o
b110 t
b0 v
b101 y
b1111111111111111 O
19
18
17
16
15
14
13
12
11
10
1/
1.
1-
1,
1+
1*
#400000
0%
0C
b100011 <
#405000
1%
1C
b11101 =
b100 >
b10 T
b11 P
b1 c
b0 e
b0 f
b0 h
b0 i
b0 k
b0 l
b0 o
b100 p
b1111110000000100 q
b111 t
b110 y
b0 {
#410000
0%
0C
b100100 <
#415000
1%
1C
b11110 =
b101 >
b11 T
b100 P
b10 c
b1 o
b0 q
b0 t
b100 u
b1111111100 v
b111 y
b0 O
09
08
07
06
05
04
03
02
01
00
0/
0.
0-
0,
0+
0*
#420000
0%
0C
b11111111 (
b100101 <
1M
1L
1K
1J
1I
1H
1G
1F
#425000
1%
1C
b11111 =
b110 >
b11111111 V
b11111111 W
b11111111 X
b100 T
b101 P
b11 c
b10 o
b1 t
b0 v
b0 y
b100 z
b1111111100 {
#430000
0%
0C
b100110 <
#435000
1%
1C
b100000 =
b11111111111111111111111111111111 >
b11 ?
b101 T
b110 P
b100 c
b11111111 g
b11111111 j
b11111111 m
b11111111 [
b11111111 ^
b11111111 a
b11 o
b10 t
b1 y
b0 {
#440000
0%
0C
b100111 <
#445000
1%
1C
b100001 =
b0 >
b110 T
b111 P
b101 c
b11111111 f
b11111111 i
b11111111 l
b11111111 Z
b11111111 ]
b11111111 `
b100 o
b1111111100 q
b11 t
b10 y
#450000
0%
0C
b101000 <
#455000
1%
1C
b100010 =
b1 >
b111 T
b0 P
b101 Q
b110 c
b11111111 e
b11111111 h
b11111111 k
b11111111 Y
b11111111 \
b11111111 _
b101 o
b100 t
b1111111100 v
b11 y
#460000
0%
0C
b0 (
b101001 <
0M
0L
0K
0J
0I
0H
0G
0F
#465000
1%
1C
b100011 =
b10 >
b0 V
b0 W
b0 X
b0 T
b101 U
b1 P
b111 c
b110 o
b0 q
b101 t
b100 y
b1111111100 {
#470000
0%
0C
b101010 <
#475000
1%
1C
b100100 =
b11 >
b1 T
b10 P
b0 c
b101 d
b0 g
b0 j
b0 m
b0 Y
b0 Z
b0 [
b0 \
b0 ]
b0 ^
b0 _
b0 `
b0 a
b111 o
b110 t
b0 v
b101 y
b1111111111111111 O
19
18
17
16
15
14
13
12
11
10
1/
1.
1-
1,
1+
1*
#480000
0%
0C
b101011 <
#485000
1%
1C
b100101 =
b100 >
b10 T
b11 P
b1 c
b0 e
b0 f
b0 h
b0 i
b0 k
b0 l
b0 o
b101 p
b1111110000000100 q
b111 t
b110 y
b0 {
#490000
0%
0C
b101100 <
#495000
1%
1C
b100110 =
b101 >
b11 T
b100 P
b10 c
b1 o
b0 q
b0 t
b101 u
b1111111100 v
b111 y
b0 O
09
08
07
06
05
04
03
02
01
00
0/
0.
0-
0,
0+
0*
#500000
0%
0C
b11111111 (
b101101 <
1M
1L
1K
1J
1I
1H
1G
1F
#505000
1%
1C
b100111 =
b110 >
b11111111 V
b11111111 W
b11111111 X
b100 T
b101 P
b11 c
b10 o
b1 t
b0 v
b0 y
b101 z
b1111111100 {
#510000
0%
0C
b101110 <
#515000
1%
1C
b101000 =
b11111111111111111111111111111111 >
b100 ?
b101 T
b110 P
b100 c
b11111111 g
b11111111 j
b11111111 m
b11111111 [
b11111111 ^
b11111111 a
b11 o
b10 t
b1 y
b0 {
#520000
0%
0C
b101111 <
#525000
1%
1C
b101001 =
b0 >
b110 T
b111 P
b101 c
b11111111 f
b11111111 i
b11111111 l
b11111111 Z
b11111111 ]
b11111111 `
b100 o
b1111111100 q
b11 t
b10 y
#530000
0%
0C
b110000 <
#535000
1%
1C
b101010 =
b1 >
b111 T
b0 P
b0 Q
b110 c
b11111111 e
b11111111 h
b11111111 k
b11111111 Y
b11111111 \
b11111111 _
b101 o
b100 t
b1111111100 v
b11 y
#540000
0%
0C
0'
b0 (
0E
0M
0L
0K
0J
0I
0H
0G
0F
#545000
1%
1C
b101011 =
b10 >
0S
b111 c
b110 o
b0 q
b101 t
b100 y
b1111111100 {
#550000
0%
0C
#555000
1%
1C
b101100 =
b11 >
0b
b111 o
b110 t
b0 v
b101 y
b1111111111111111 O
19
18
17
16
15
14
13
12
11
10
1/
1.
1-
1,
1+
1*
#560000
0%
0C
#565000
1%
1C
b101101 =
b100 >
0n
b111 t
b110 y
b0 {
#570000
0%
0C
#575000
1%
1C
b101110 =
b101 >
0s
b111 y
b0 O
09
08
07
06
05
04
03
02
01
00
0/
0.
0-
0,
0+
0*
#580000
0%
0C
#585000
1%
1C
b101111 =
b110 >
0x
#590000
0%
0C
#595000
1%
1C
b110000 =
0N
0)
